README.md
setup.py
srudp/__init__.py
srudp/chunkedsock.py
srudp.egg-info/PKG-INFO
srudp.egg-info/SOURCES.txt
srudp.egg-info/dependency_links.txt
srudp.egg-info/requires.txt
srudp.egg-info/top_level.txt