Metadata-Version: 2.1
Name: srudp
Version: 0.3.4
Summary: secure reliable udp socket implemented by PurePython
Home-page: https://github.com/namuyan/srudp
Author: namuyan
License: MIT Licence
Keywords: RUDP UDP P2P hole-punching
Platform: UNKNOWN
Classifier: Typing :: Typed
Classifier: Topic :: Internet
Classifier: Framework :: AsyncIO
Classifier: Topic :: System :: Networking
Classifier: Development Status :: 3 - Alpha
Classifier: Programming Language :: Python :: 3
Classifier: License :: OSI Approved :: MIT License
Requires-Python: >=3.6
